CHANGES.rst
LICENSE
README.rst
requirements.txt
setup.cfg
setup.py
stdeb.cfg
batchhttp/__init__.py
batchhttp/batchproxy.py
batchhttp/client.py
batchhttp/multipart.py
doc/client.rst
doc/conf.py
doc/index.rst
doc/multipart.rst
doc/readme_from_docstring.py
doc/requirements.txt
doc/exts/document_init_methods.py
tests/__init__.py
tests/client_with.py
tests/requirements.txt
tests/test_client.py
tests/utils.py