Metadata-Version: 1.1
Name: batchhttp
Version: 1.1.1
Summary: Parallel HTTP through MIME multipart encoding
Home-page: http://github.com/sixapart/batchhttp
Author: Six Apart Ltd.
Author-email: python@sixapart.com
License: UNKNOWN
Platform: UNKNOWN
Classifier: Development Status :: 4 - Beta
Classifier: Environment :: Console
Classifier: Environment :: Web Environment
Classifier: Intended Audience :: Developers
Classifier: License :: OSI Approved :: BSD License
Classifier: Operating System :: MacOS :: MacOS X
Classifier: Operating System :: POSIX
Classifier: Programming Language :: Python
Classifier: Topic :: Internet :: WWW/HTTP
Requires: httplib2(>=0.6.0)
Provides: batchhttp
